[
  {
    "title": "Top 10 delivery tips for a smooth experience",
    "content": "",
    "url": "top-10-delivery-tips-for-a-smooth-experience",
    "img": ""
  },
  {
    "title": "How to choose the right delivery service for your need",
    "content": "",
    "url": "how-to-choose-the-right-delivery-service-for-your-need"
  },
  {
    "title": "The impact of E-commerce on the delivery industry",
    "content": "",
    "url": "the-impact-of-e-commerce-on-the-delivery-industry"
  },
  {
    "title": "The future of delivery services: emerging technologies and trends",
    "content": "",
    "url": "the-future-of-delivery-services:-emerging-technologies-and-trends"
  },
  {
    "title": "Safe and secure delivery: best practices and recommendationse",
    "content": "",
    "url": "safe-and-secure-delivery:-best-practices-and-recommendations"
  },
  {
    "title": "Eco-friendly delivery options and practices",
    "content": "",
    "url": "eco-friendly-delivery-options-and-practices"
  },
  {
    "title": "The importance of reliable tracking and delivery updates",
    "content": "",
    "url": "the-importance-of-reliable-tracking-and-delivery-updates"
  },
  {
    "title": "How to handle delivery delays and disruptions",
    "content": "",
    "url": "how-to-handle-delivery-delays-and-disruptions"
  },
  {
    "title": "Behind the scenes of a delivery company: a day in the life",
    "content": "",
    "url": "behind-the-scenes-of-a-delivery-company:-a-day-in-the-life"
  },
  {
    "title": "How to pack and prepare items for safe and secure delivery",
    "content": "",
    "url": "how-to-pack-and-prepare-items-for-safe-and-secure-delivery"
  }
]
